cyaudit/__init__.py
cyaudit/__main__.py
cyaudit/config.py
cyaudit/constants.py
cyaudit/create_action.py
cyaudit/git_tools.py
cyaudit/github_project_utils.py
cyaudit/logging.py
cyaudit/commands/add_team.py
cyaudit/commands/clone.py
cyaudit/commands/init.py
cyaudit/commands/report.py
cyaudit/commands/setup.py
cyaudit/commands/source.py
cyaudit/report_template/output/.gitignore
cyaudit/report_template/source/about_cyfrin.md
cyaudit/report_template/source/additional_comments.md
cyaudit/report_template/source/appendix.md
cyaudit/report_template/source/assisting_auditors.md
cyaudit/report_template/source/audit_scope.md
cyaudit/report_template/source/disclaimer.md
cyaudit/report_template/source/executive_summary.md
cyaudit/report_template/source/lead_auditors.md
cyaudit/report_template/source/protocol_summary.md
cyaudit/report_template/source/report.md
cyaudit/report_template/source/severity_counts.toml
cyaudit/report_template/source/summary_information.toml
cyaudit/report_template/templates/main.tex
cyaudit/report_template/templates/post_report.tex
cyaudit/report_template/templates/pre_report.tex
cyaudit/report_template/templates/risk_classification.tex
cyaudit/report_template/templates/summary.tex
cyaudit/report_template/templates/title.tex
cyaudit/report_template/templates/img/cyfrin-logo.png
cyaudit/report_template/working/.gitignore
cyaudit/report_template/working/main.tex
cyaudit/report_template/working/post_report.tex
cyaudit/report_template/working/pre_report.tex
cyaudit/report_template/working/risk_classification.tex
cyaudit/report_template/working/summary.tex
cyaudit/report_template/working/title.tex
cyaudit/report_template/working/img/cyfrin-logo.png
cyaudit/utils/create_report.py
cyaudit/utils/pandoc-image.py
cyaudit/utils/pandoc-minted.py
cyaudit-0.1.0.dist-info/METADATA
cyaudit-0.1.0.dist-info/WHEEL
cyaudit-0.1.0.dist-info/entry_points.txt
cyaudit-0.1.0.dist-info/licenses/LICENCE-APACHE
cyaudit-0.1.0.dist-info/licenses/LICENCE-MIT
cyaudit-0.1.0.dist-info/RECORD
