Metadata-Version: 2.4
Name: cyaudit
Version: 0.1.0
Summary: Add your description here
License-File: LICENCE-APACHE
License-File: LICENCE-MIT
Keywords: audit,cyfrin,github
Classifier: Development Status :: 3 - Alpha
Classifier: Intended Audience :: Developers
Classifier: License :: OSI Approved :: MIT License
Classifier: Programming Language :: Python :: 3
Classifier: Programming Language :: Python :: 3.13
Requires-Python: >=3.9
Requires-Dist: gql>=3.5.0
Requires-Dist: pandocfilters>=1.5.1
Requires-Dist: pygithub>=2.5.0
Requires-Dist: python-dateutil>=2.9.0.post0
Requires-Dist: requests-toolbelt>=1.0.0
Requires-Dist: tomli-w>=1.2.0
